{
    "lightsabers.enable": {
        "sounds": [
            "lightsaber/enable"
        ]
    },

    "lightsabers.disable": {
        "sounds": [
            "lightsaber/disable"
        ]
    },

    "lightsabers.hit": {
        "sounds": [
            "lightsaber/hit_01"
        ]
    },

    "lightsabers.crit": {
        "sounds": [
            "lightsaber/crit_01",
            "lightsaber/crit_02",
            "lightsaber/crit_03"
        ]
    },

    "lightsabers.move": {
        "sounds": [
            "lightsaber/move_01",
            "lightsaber/move_02"
        ]
    },

    "lightsaber.qwartz.all": {
        "sounds": [
            "lightsaber/qwartz/halapeneu"
        ]
    }
}
